{
  "date": "2021-02-12T18:36:02.684Z",
  "title": "Receitas de Maracujá",
  "thumbnail": "/img/uploads/8-2-.jpg",
  "body": "## Receitas de Maracujá\n\n#### Gin Tônica\n\n\\- 60 ml de gin\n\n\\- 30 ml de xarope de maracujá\n\n\\- 100 ml de tônica\n\n\\- 1 ramo de alecrim\n\n\n\n#### Passion Mule\n\n60 ml de vodka\n\n30 ml de xarope de maracujá\n\n100 ml de água com gás\n\n1 ramo de alecrim\n\n\n\n#### Passion Mojito\n\n\\- 60 ml de rum\n\n\\- 30 ml de xarope de maracujá\n\n\\- 100 ml de soda\n\n\\- 1 ramo de alecrim\n\n\n\n#### Caipimaracujá\n\n60 ml de cachaça\n\n30 ml de xarope de maracujá\n\n100 ml de água com gás\n\n1 ramo de alecrim",
  "description": "Veja as receitas de Drinks de Maracujá e faça bons drinks com muita simplicidade usando os nossos produtos.",
  "meta_description": "Veja as receitas de Drinks de Maracujá e faça bons drinks com muita simplicidade usando os nossos produtos.",
  "meta_title": "Drinks de Maracujá",
  "sections": [
    {
      "type": "collection-shelf",
      "shuffle": false,
      "limit": 12,
      "page": 1,
      "collection_id": "600af70d69274c73fcfaf5b4:categories:Xaropes:/xaropes",
      "sort": "views"
    }
  ]
}